{
    "image_configs": [
        {
            "filename": "016242164.main.jpg",
            "method": "points",
            "points": [
                {
                    "x": 94,
                    "y": 248,
                    "radius": 7
                },
                {
                    "x": 333,
                    "y": 218,
                    "radius": 7
                },
                {
                    "x": 321,
                    "y": 204,
                    "radius": 7
                },
                {
                    "x": 363,
                    "y": 255,
                    "radius": 7
                },
                {
                    "x": 244,
                    "y": 223,
                    "radius": 7
                },
                {
                    "x": 296,
                    "y": 155,
                    "radius": 7
                },
                {
                    "x": 298,
                    "y": 170,
                    "radius": 7
                },
                {
                    "x": 91,
                    "y": 213,
                    "radius": 7
                },
                {
                    "x": 88,
                    "y": 227,
                    "radius": 7
                },
                {
                    "x": 295,
                    "y": 217,
                    "radius": 7
                },
                {
                    "x": 302,
                    "y": 183,
                    "radius": 7
                },
                {
                    "x": 307,
                    "y": 197,
                    "radius": 7
                },
                {
                    "x": 293,
                    "y": 195,
                    "radius": 7
                },
                {
                    "x": 291,
                    "y": 182,
                    "radius": 7
                },
                {
                    "x": 268,
                    "y": 199,
                    "radius": 7
                },
                {
                    "x": 263,
                    "y": 273,
                    "radius": 7
                },
                {
                    "x": 336,
                    "y": 199,
                    "radius": 7
                },
                {
                    "x": 319,
                    "y": 186,
                    "radius": 7
                },
                {
                    "x": 88,
                    "y": 274,
                    "radius": 7
                },
                {
                    "x": 366,
                    "y": 277,
                    "radius": 7
                },
                {
                    "x": 180,
                    "y": 233,
                    "radius": 7
                },
                {
                    "x": 226,
                    "y": 246,
                    "radius": 7
                },
                {
                    "x": 287,
                    "y": 242,
                    "radius": 7
                },
                {
                    "x": 235,
                    "y": 199,
                    "radius": 7
                },
                {
                    "x": 346,
                    "y": 226,
                    "radius": 7
                },
                {
                    "x": 352,
                    "y": 213,
                    "radius": 7
                },
                {
                    "x": 320,
                    "y": 224,
                    "radius": 7
                },
                {
                    "x": 304,
                    "y": 142,
                    "radius": 7
                }
            ]
        },
        {
            "filename": "image.png",
            "method": "points",
            "points": [
                {
                    "x": 321,
                    "y": 603,
                    "radius": 7
                },
                {
                    "x": 240,
                    "y": 599,
                    "radius": 7
                },
                {
                    "x": 237,
                    "y": 576,
                    "radius": 7
                },
                {
                    "x": 442,
                    "y": 575,
                    "radius": 7
                },
                {
                    "x": 410,
                    "y": 525,
                    "radius": 7
                },
                {
                    "x": 412,
                    "y": 543,
                    "radius": 7
                },
                {
                    "x": 438,
                    "y": 606,
                    "radius": 7
                },
                {
                    "x": 469,
                    "y": 625,
                    "radius": 7
                },
                {
                    "x": 238,
                    "y": 631,
                    "radius": 7
                },
                {
                    "x": 390,
                    "y": 575,
                    "radius": 7
                },
                {
                    "x": 435,
                    "y": 566,
                    "radius": 7
                },
                {
                    "x": 418,
                    "y": 562,
                    "radius": 7
                },
                {
                    "x": 376,
                    "y": 562,
                    "radius": 7
                },
                {
                    "x": 465,
                    "y": 606,
                    "radius": 7
                },
                {
                    "x": 430,
                    "y": 550,
                    "radius": 7
                },
                {
                    "x": 378,
                    "y": 606,
                    "radius": 7
                },
                {
                    "x": 344,
                    "y": 595,
                    "radius": 7
                },
                {
                    "x": 314,
                    "y": 584,
                    "radius": 7
                },
                {
                    "x": 272,
                    "y": 600,
                    "radius": 7
                },
                {
                    "x": 263,
                    "y": 563,
                    "radius": 7
                },
                {
                    "x": 388,
                    "y": 620,
                    "radius": 7
                },
                {
                    "x": 379,
                    "y": 630,
                    "radius": 7
                },
                {
                    "x": 456,
                    "y": 575,
                    "radius": 7
                },
                {
                    "x": 424,
                    "y": 576,
                    "radius": 7
                },
                {
                    "x": 412,
                    "y": 574,
                    "radius": 7
                },
                {
                    "x": 409,
                    "y": 570,
                    "radius": 7
                },
                {
                    "x": 413,
                    "y": 518,
                    "radius": 7
                },
                {
                    "x": 418,
                    "y": 508,
                    "radius": 7
                }
            ]
        }
    ]
}